LICENSE
MANIFEST.in
README.rst
setup.py
common/__init__.py
common/settings.py
data/__init__.py
data/base.py
data/builddb.py
data/delete_row.py
data/get_row.py
data/save_row.py
data/search_rows.py
data/validate_fields.py
deploy/__init__.py
deploy/fabfile.py
docs/Makefile
docs/coding-standards.rst
docs/command-line.rst
docs/conf.py
docs/folder-structure.rst
docs/index.rst
docs/install.rst
docs/make.bat
docs/program-flow.rst
docs/setup.rst
docs/steps.rst
docs/_build/doctrees/coding-standards.doctree
docs/_build/doctrees/command-line.doctree
docs/_build/doctrees/environment.pickle
docs/_build/doctrees/folder-structure.doctree
docs/_build/doctrees/index.doctree
docs/_build/doctrees/install.doctree
docs/_build/doctrees/program-flow.doctree
docs/_build/doctrees/setup.doctree
docs/_build/doctrees/steps.doctree
docs/_build/html/.buildinfo
docs/_build/html/coding-standards.html
docs/_build/html/command-line.html
docs/_build/html/folder-structure.html
docs/_build/html/genindex.html
docs/_build/html/index.html
docs/_build/html/install.html
docs/_build/html/objects.inv
docs/_build/html/program-flow.html
docs/_build/html/search.html
docs/_build/html/searchindex.js
docs/_build/html/setup.html
docs/_build/html/steps.html
docs/_build/html/_sources/coding-standards.txt
docs/_build/html/_sources/command-line.txt
docs/_build/html/_sources/folder-structure.txt
docs/_build/html/_sources/index.txt
docs/_build/html/_sources/install.txt
docs/_build/html/_sources/program-flow.txt
docs/_build/html/_sources/setup.txt
docs/_build/html/_sources/steps.txt
docs/_build/html/_static/ajax-loader.gif
docs/_build/html/_static/alabaster.css
docs/_build/html/_static/basic.css
docs/_build/html/_static/comment-bright.png
docs/_build/html/_static/comment-close.png
docs/_build/html/_static/comment.png
docs/_build/html/_static/custom.css
docs/_build/html/_static/doctools.js
docs/_build/html/_static/down-pressed.png
docs/_build/html/_static/down.png
docs/_build/html/_static/file.png
pymixup.egg-info/PKG-INFO
pymixup.egg-info/SOURCES.txt
pymixup.egg-info/dependency_links.txt
pymixup.egg-info/pbr.json
pymixup.egg-info/requires.txt
pymixup.egg-info/top_level.txt
