Metadata-Version: 1.1
Name: pymixup
Version: 1.0.2
Summary: An app to obfuscate Python projects
Home-page: http://github.com/rdevost/pymixup
Author: Richard DeVost
Author-email: richard@devost.org
License: UNKNOWN
Keywords: python obfuscate pymixup
Platform: UNKNOWN
Classifier: Intended Audience :: Developers
Classifier: Programming Language :: Python
Classifier: Programming Language :: Python :: 2
Classifier: Programming Language :: Python :: 2.7
Classifier: Operating System :: OS Independent
Classifier: Topic :: Software Development
